{"stats":{"minecraft:used":{"minecraft:moss_block":146,"minecraft:oak_trapdoor":57,"minecraft:spruce_leaves":39,"minecraft:torch":46,"minecraft:ender_eye":87,"minecraft:glowstone":124,"minecraft:flint_and_steel":1,"minecraft:spruce_wood":1,"minecraft:stripped_oak_wood":13,"minecraft:lantern":2,"minecraft:oak_stairs":356,"minecraft:oak_planks":12,"minecraft:spruce_pressure_plate":3,"minecraft:oak_wood":12,"minecraft:end_portal_frame":108,"minecraft:spruce_planks":583,"minecraft:tinted_glass":1,"minecraft:stone":7,"minecraft:spruce_trapdoor":58,"minecraft:spruce_log":68},"minecraft:picked_up":{"minecraft:torch":9},"minecraft:custom":{"minecraft:time_since_rest":54935,"minecraft:crouch_one_cm":3014,"minecraft:sprint_one_cm":716,"minecraft:play_time":54935,"minecraft:walk_one_cm":76835,"minecraft:sneak_time":5481,"minecraft:jump":107,"minecraft:leave_game":3,"minecraft:time_since_death":54935,"minecraft:total_world_time":267727,"minecraft:fly_one_cm":570459}},"DataVersion":3700}